carthage_copy_frameworks/__init__.py
carthage_copy_frameworks-2.0.0.dist-info/LICENSE.txt
carthage_copy_frameworks-2.0.0.dist-info/METADATA
carthage_copy_frameworks-2.0.0.dist-info/WHEEL
carthage_copy_frameworks-2.0.0.dist-info/entry_points.txt
carthage_copy_frameworks-2.0.0.dist-info/top_level.txt
carthage_copy_frameworks-2.0.0.dist-info/RECORD
