Metadata-Version: 2.1
Name: carthage-copy-frameworks
Version: 2.0.0
Summary: carthage-copy-frameworks is an helper script that automatically copies every framework below Carthage/Build/iOS
Home-page: https://github.com/lvillani/carthage-copy-frameworks
Author: Lorenzo Villani
Author-email: lorenzo@villani.me
License: MIT
Keywords: apple build carthage helper ios
Platform: UNKNOWN
Classifier: Development Status :: 5 - Production/Stable
Classifier: Intended Audience :: Developers
Classifier: License :: OSI Approved :: MIT License
Classifier: Programming Language :: Python :: 3
Classifier: Topic :: Software Development :: Build Tools
